meetbopi/__init__.py
meetbopi/bopi_client.py
meetbopi/exceptions.py
meetbopi/helper.py
meetbopi/relay.py
meetbopi/sensors_state.py
meetbopi-1.0.1.dist-info/METADATA
meetbopi-1.0.1.dist-info/WHEEL
meetbopi-1.0.1.dist-info/licenses/LICENSE.md
meetbopi-1.0.1.dist-info/RECORD
