Metadata-Version: 2.4
Name: meetbopi
Version: 1.0.1
Summary: Asynchronous Python client for the Bopi API.
License-Expression: MIT
License-File: LICENSE.md
Keywords: meetbopi,bopi,api,async,client
Author: Matthieu Derasse
Author-email: opensource@derasse.fr
Maintainer: Matthieu Derasse
Maintainer-email: opensource@derasse.fr
Requires-Python: >=3.11
Classifier: Development Status :: 4 - Beta
Classifier: Framework :: AsyncIO
Classifier: Intended Audience :: Developers
Classifier: Natural Language :: English
Classifier: Programming Language :: Python :: 3.11
Classifier: Programming Language :: Python :: 3.12
Classifier: Programming Language :: Python :: 3.13
Classifier: Programming Language :: Python :: 3.14
Classifier: Programming Language :: Python :: 3
Classifier: Topic :: Software Development :: Libraries :: Python Modules
Requires-Dist: aiohttp (>=3.9.0)
Requires-Dist: yarl (>=1.9.0)
Project-URL: Bug Tracker, https://github.com/mderasse/python-bopi/issues
Project-URL: Changelog, https://github.com/mderasse/python-bopi/releases
Project-URL: Documentation, https://github.com/mderasse/python-bopi
Project-URL: Homepage, https://github.com/mderasse/python-bopi
Project-URL: Repository, https://github.com/mderasse/python-bopi
